roentgen/__init__.py
roentgen/absorption/__init__.py
roentgen/absorption/material.py
roentgen/data/README.rst
roentgen/data/compounds_mixtures.csv
roentgen/data/electron_binding_energies.csv
roentgen/data/elements.csv
roentgen/data/emission_energies.csv
roentgen/data/emission_lines.csv
roentgen/data/nuclides_list.csv
roentgen/data/siegbahn_to_iupac.csv
roentgen/data/compounds_mixtures/a150.csv
roentgen/data/compounds_mixtures/adipose.csv
roentgen/data/compounds_mixtures/air.csv
roentgen/data/compounds_mixtures/alanine.csv
roentgen/data/compounds_mixtures/b100.csv
roentgen/data/compounds_mixtures/bakelite.csv
roentgen/data/compounds_mixtures/blood.csv
roentgen/data/compounds_mixtures/bone.csv
roentgen/data/compounds_mixtures/brain.csv
roentgen/data/compounds_mixtures/breast.csv
roentgen/data/compounds_mixtures/c552.csv
roentgen/data/compounds_mixtures/calcium_fluoride.csv
roentgen/data/compounds_mixtures/calcium_sulfate.csv
roentgen/data/compounds_mixtures/cdte.csv
roentgen/data/compounds_mixtures/ceric.csv
roentgen/data/compounds_mixtures/cesium_iodide.csv
roentgen/data/compounds_mixtures/concrete.csv
roentgen/data/compounds_mixtures/concrete_barite.csv
roentgen/data/compounds_mixtures/eye.csv
roentgen/data/compounds_mixtures/fricke.csv
roentgen/data/compounds_mixtures/gadox.csv
roentgen/data/compounds_mixtures/gafchromic.csv
roentgen/data/compounds_mixtures/gallium_arsenide.csv
roentgen/data/compounds_mixtures/kodak.csv
roentgen/data/compounds_mixtures/lead_glass.csv
roentgen/data/compounds_mixtures/lithium_fluoride.csv
roentgen/data/compounds_mixtures/lithium_tetraborate.csv
roentgen/data/compounds_mixtures/lung.csv
roentgen/data/compounds_mixtures/magnesium_tetraborate.csv
roentgen/data/compounds_mixtures/mercuric_iodide.csv
roentgen/data/compounds_mixtures/muscle.csv
roentgen/data/compounds_mixtures/mylar.csv
roentgen/data/compounds_mixtures/nylonfilm.csv
roentgen/data/compounds_mixtures/ovary.csv
roentgen/data/compounds_mixtures/photo_emulsion.csv
roentgen-2.4.0.dist-info/METADATA
roentgen-2.4.0.dist-info/WHEEL
roentgen-2.4.0.dist-info/licenses/AUTHORS.rst
roentgen-2.4.0.dist-info/licenses/LICENSE.rst
roentgen-2.4.0.dist-info/RECORD
