Metadata-Version: 2.4
Name: roentgen
Version: 2.4.0
Summary: A Python package for the quantitative analysis of the interaction of energetic x-rays with matter. This package is named after one of the discoverers of X-rays, Wilhelm Rontgen.
Author-email: Steven Christe <steven.d.christe@nasa.gov>, Nabil Freij <nabobalis@users.noreply.github.com>, Shane Maloney <samaloney@users.noreply.github.com>, Dan Ryan <DanRyanIrish@users.noreply.github.com>
License: License
License-File: AUTHORS.rst
License-File: LICENSE.rst
Keywords: python,roentgen,x-ray
Classifier: Development Status :: 5 - Production/Stable
Classifier: Intended Audience :: Science/Research
Classifier: License :: OSI Approved :: Apache Software License
Classifier: Natural Language :: English
Classifier: Operating System :: OS Independent
Classifier: Programming Language :: Python :: 3 :: Only
Classifier: Programming Language :: Python :: 3.10
Classifier: Topic :: Scientific/Engineering :: Astronomy
Classifier: Topic :: Scientific/Engineering :: Medical Science Apps.
Classifier: Topic :: Scientific/Engineering :: Physics
Requires-Python: >=3.11
Requires-Dist: astropy>=7.2.0
Requires-Dist: scipy>=1.16.3
Provides-Extra: gui
Requires-Dist: bokeh>=3.8.1; extra == 'gui'
